T02/T02_Stopwatch_Project/T02_Stopwatch_Project.srcs/sources_1/new/debounce.v
`timescale 1ns / 1ps
//////////////////////////////////////////////////////////////////////////////////
// Company: 
// Engineer: 
// 
// Create Date: 06.03.2025 12:55:38
// Design Name: 
// Module Name: debounce
// Project Name: 
// Target Devices: 
// Tool Versions: 
// Description: 
// 
// Dependencies: 
// 
// Revision:
// Revision 0.01 - File Created
// Additional Comments:
// 
//////////////////////////////////////////////////////////////////////////////////

module debounce (
    input wire clk,        // System clock (e.g., 100 MHz on Basys 3)
    input wire reset,      // Reset signal
    input wire button_in,  // Raw button input
    output reg button_out  // Debounced button output
);

    reg [19:0] count;      // 20-bit counter for debouncing
    reg button_prev;        // Previous state of the button

    always @(posedge clk or posedge reset) begin
        // Reset counter and button statuses if reset pin asserted
        if (reset) begin
            count <= 20'b0;
            button_prev <= 1'b0;
            button_out <= 1'b0;
        end else begin
            button_prev <= button_in;
            // Set counter to 0 when button state changes
            if (button_prev != button_in) begin
                count <= 20'b0;
            // If counter hits maximum, set button output to previous button state
            end else if (count == 20'h0000F) begin
                button_out <= button_prev;
            // Increment counter
            end else begin
                count <= count + 1;
            end
        end
    end

endmodule

T02/T02_Stopwatch_Project/T02_Stopwatch_Project.srcs/sim_2/new/debounce_tb.v
`timescale 1ns / 1ps
//////////////////////////////////////////////////////////////////////////////////
// Company: 
// Engineer: 
// 
// Create Date: 31.03.2025 15:45:12
// Design Name: 
// Module Name: debounce_tb
// Project Name: 
// Target Devices: 
// Tool Versions: 
// Description: 
// 
// Dependencies: 
// 
// Revision:
// Revision 0.01 - File Created
// Additional Comments:
// 
//////////////////////////////////////////////////////////////////////////////////

`timescale 1ns / 1ps
//////////////////////////////////////////////////////////////////////////////////
// Company: 
// Engineer: 
// 
// Create Date: 31.03.2025 15:03:16
// Design Name: 
// Module Name: debounce_tb
// Project Name: 
// Target Devices: 
// Tool Versions: 
// Description: 
// 
// Dependencies: 
// 
// Revision:
// Revision 0.01 - File Created
// Additional Comments:
// 
//////////////////////////////////////////////////////////////////////////////////

module tb;
    // Inputs
    reg clk;
    reg reset;
    reg button_in;
    
    // Outputs
    wire button_out;

    debounce dut(sw, led);
    
    // Clock generation
always begin
    #2 clk = ~clk;
end

initial begin
    $dumpfile("tb.vcd");
    $dumpvars(0,tb);
    $dumpon;
    
    // Initialise signals at start of simulation
    clk = 0;
    reset = 0;
    button_in = 0;
    
    // Simulation
    
    #10 $finish;

    $dumpoff;
end

endmodule

T02/T02_Stopwatch_Project/T02_Stopwatch_Project.sim/sim_2/behav/xsim/tb.vcd
$date
   Mon Mar 31 16:07:12 2025
$end

$version
  2023.2
  $dumpfile ("tb.vcd") 
$end

$timescale
  1ps
$end

$scope module tb $end
$var reg 1 ! clk $end
$var reg 1 " reset $end
$var reg 1 # button_in $end
$var wire 1 $ button_out $end
$scope module dut $end
$var wire 1 % clk $end
$var wire 1 & reset $end
$var wire 1 ' button_in $end
$var reg 1 ( button_out $end
$var reg 20 ) count [19:0] $end
$var reg 1 * button_prev $end
$upscope $end
$upscope $end
$enddefinitions $end

#0
$dumpvars
0!
0"
0#
x$
0%
0&
0'
x(
bx )
x*
$end

#1000
1!
1"
0$
1%
1&
0(
b0 )
0*

#2000
0!
0%

#3000
1!
1%

#4000
0!
0%

#5000
1!
1%

#6000
0!
0"
0%
0&

#7000
1!
1#
1%
1'
1*

#8000
0!
0%

#9000
1!
1%
b1 )

#10000
0!
0%

#11000
1!
1%
b10 )

#12000
0!
0%

#13000
1!
1%
b11 )

#14000
0!
0%

#15000
1!
1%
b100 )

#16000
0!
0%

#17000
1!
1%
b101 )

#18000
0!
0%

#19000
1!
1%
b110 )

#20000
0!
0%

#21000
1!
1%
b111 )

#22000
0!
0#
0%
0'

#23000
1!
1%
b0 )
0*

#24000
0!
0%

#25000
1!
1%
b1 )

#26000
0!
1#
0%
1'

#27000
1!
1%
b0 )
1*

#28000
0!
0%

#29000
1!
1%
b1 )

#30000
0!
0%

#31000
1!
1%
b10 )

#32000
0!
0%

#33000
1!
1%
b11 )

#34000
0!
0%

#35000
1!
1%
b100 )

#36000
0!
0%

#37000
1!
1%
b101 )

#38000
0!
0%

#39000
1!
1%
b110 )

#40000
0!
0%

#41000
1!
1%
b111 )

#42000
0!
0%

#43000
1!
1%
b1000 )

#44000
0!
0%

#45000
1!
1%
b1001 )

#46000
0!
0%

#47000
1!
1%
b1010 )

#48000
0!
0%

#49000
1!
1%
b1011 )

#50000
0!
0%

#51000
1!
1%
b1100 )

#52000
0!
0%

#53000
1!
1%
b1101 )

#54000
0!
0%

#55000
1!
1%
b1110 )

#56000
0!
0%

#57000
1!
1%
b1111 )

#58000
0!
0%

#59000
1!
1$
1%
1(

#60000
0!
0%

#61000
1!
1%

#62000
0!
0%

#63000
1!
1%

#64000
0!
0%

#65000
1!
1%

#66000
0!
0%

#67000
1!
1%

#68000
0!
0%

#69000
1!
1%

#70000
0!
0%

#71000
1!
1%

#72000
0!
0%

#73000
1!
1%

#74000
0!
0%

#75000
1!
1%

#76000
0!
0%

#77000
1!
1%

#78000
0!
0%

#79000
1!
1%

#80000
0!
0%

#81000
1!
1%

#82000
0!
0%

#83000
1!
1%

#84000
0!
0%

#85000
1!
1%

#86000
0!
0%

#87000
1!
1%

#88000
0!
0%

#89000
1!
1%

#90000
0!
0#
0%
0'

#91000
1!
1%
b0 )
0*

#92000
0!
0%

#93000
1!
1%
b1 )

#94000
0!
0%

#95000
1!
1%
b10 )

#96000
0!
0%

#97000
1!
1%
b11 )

#98000
0!
0%

#99000
1!
1%
b100 )

#100000
0!
0%

#101000
1!
1%
b101 )

#102000
0!
0%

#103000
1!
1%
b110 )

#104000
0!
0%

#105000
1!
1%
b111 )

#106000
0!
0%

#107000
1!
1%
b1000 )

#108000
0!
0%

#109000
1!
1%
b1001 )

#110000
0!
0%

#111000
1!
1%
b1010 )

#112000
0!
0%

#113000
1!
1%
b1011 )

#114000
0!
0%

#115000
1!
1%
b1100 )

#116000
0!
0%

#117000
1!
1%
b1101 )

#118000
0!
0%

#119000
1!
1%
b1110 )

#120000
0!
0%

#121000
1!
1%
b1111 )

#122000
0!
0%

#123000
1!
0$
1%
0(

