T02/T02_Stopwatch_Project/T02_Stopwatch_Project.srcs/sources_1/new/clk_100M_to_1k.v
`timescale 1ns / 1ps
//////////////////////////////////////////////////////////////////////////////////
// Company: 
// Engineer: 
// 
// Create Date: 31.03.2025 16:45:16
// Design Name: 
// Module Name: clk_100M_to_1k
// Project Name: 
// Target Devices: 
// Tool Versions: 
// Description: 
// 
// Dependencies: 
// 
// Revision:
// Revision 0.01 - File Created
// Additional Comments:
// 
//////////////////////////////////////////////////////////////////////////////////

module clk_100M_to_1k(
    input clk_100M,     // Input clock from the FPGA's master clock
    input rst,          // Active high reset
    output reg clk_1k   // Output clock
    );
    
    reg [16:0] counter;
    
    initial clk_1k = 0;
    initial counter = 0;
    
    always @(posedge rst, posedge clk_100M) begin
        if (rst) begin
            counter <= 0;
            clk_1k <= 0;
        end
        else begin
            if (counter == 17'h186A0) begin // For actual, h186A0 = d100000, after this number of clock cycles the 1kHz clock advances
//            if (counter == 17'd9) begin // For testbench purposes
                counter <= 0;
                clk_1k <= ~clk_1k;
            end else
                counter <= counter + 1;
        end
    end
endmodule

T02/T02_Stopwatch_Project/T02_Stopwatch_Project.srcs/clk_sims/new/tb.v
`timescale 1ns / 1ps
//////////////////////////////////////////////////////////////////////////////////
// Company: 
// Engineer: 
// 
// Create Date: 31.03.2025 21:57:10
// Design Name: 
// Module Name: tb
// Project Name: 
// Target Devices: 
// Tool Versions: 
// Description: 
// 
// Dependencies: 
// 
// Revision:
// Revision 0.01 - File Created
// Additional Comments:
// 
//////////////////////////////////////////////////////////////////////////////////


module tb;
    // Inputs
    reg clk;
    reg reset;
    
    // Outputs
    wire clk_out;

    clk_100M_to_1k dut(clk, reset, clk_out);
    
    // Clock generation
always begin
    #1 clk = ~clk;
end

initial begin
    $dumpfile("tb.vcd");
    $dumpvars(0,tb);
    $dumpon;
    
    // Initialise signals at start of simulation
    clk = 0;
    reset = 0;
    
    // Simulation
    #1 reset = 1;
    #5 reset = 0;
    #128 $finish;

    $dumpoff;
end

endmodule

T02/T02_Stopwatch_Project/T02_Stopwatch_Project.sim/clk_sims/behav/xsim/tb.vcd
$date
   Mon Mar 31 22:08:25 2025
$end

$version
  2023.2
  $dumpfile ("tb.vcd") 
$end

$timescale
  1ps
$end

$scope module tb $end
$var reg 1 ! clk $end
$var reg 1 " reset $end
$var wire 1 # clk_out $end
$scope module dut $end
$var wire 1 $ clk_100M $end
$var wire 1 % rst $end
$var reg 1 & clk_1k $end
$var reg 17 ' counter [16:0] $end
$upscope $end
$upscope $end
$enddefinitions $end

#0
$dumpvars
0!
0"
0#
0$
0%
0&
b0 '
$end

#1000
1!
1"
1$
1%

#2000
0!
0$

#3000
1!
1$

#4000
0!
0$

#5000
1!
1$

#6000
0!
0"
0$
0%

#7000
1!
1$
b1 '

#8000
0!
0$

#9000
1!
1$
b10 '

#10000
0!
0$

#11000
1!
1$
b11 '

#12000
0!
0$

#13000
1!
1$
b100 '

#14000
0!
0$

#15000
1!
1$
b101 '

#16000
0!
0$

#17000
1!
1$
b110 '

#18000
0!
0$

#19000
1!
1$
b111 '

#20000
0!
0$

#21000
1!
1$
b1000 '

#22000
0!
0$

#23000
1!
1$
b1001 '

#24000
0!
0$

#25000
1!
1#
1$
1&
b0 '

#26000
0!
0$

#27000
1!
1$
b1 '

#28000
0!
0$

#29000
1!
1$
b10 '

#30000
0!
0$

#31000
1!
1$
b11 '

#32000
0!
0$

#33000
1!
1$
b100 '

#34000
0!
0$

#35000
1!
1$
b101 '

#36000
0!
0$

#37000
1!
1$
b110 '

#38000
0!
0$

#39000
1!
1$
b111 '

#40000
0!
0$

#41000
1!
1$
b1000 '

#42000
0!
0$

#43000
1!
1$
b1001 '

#44000
0!
0$

#45000
1!
0#
1$
0&
b0 '

#46000
0!
0$

#47000
1!
1$
b1 '

#48000
0!
0$

#49000
1!
1$
b10 '

#50000
0!
0$

#51000
1!
1$
b11 '

#52000
0!
0$

#53000
1!
1$
b100 '

#54000
0!
0$

#55000
1!
1$
b101 '

#56000
0!
0$

#57000
1!
1$
b110 '

#58000
0!
0$

#59000
1!
1$
b111 '

#60000
0!
0$

#61000
1!
1$
b1000 '

#62000
0!
0$

#63000
1!
1$
b1001 '

#64000
0!
0$

#65000
1!
1#
1$
1&
b0 '

#66000
0!
0$

#67000
1!
1$
b1 '

#68000
0!
0$

#69000
1!
1$
b10 '

#70000
0!
0$

#71000
1!
1$
b11 '

#72000
0!
0$

#73000
1!
1$
b100 '

#74000
0!
0$

#75000
1!
1$
b101 '

#76000
0!
0$

#77000
1!
1$
b110 '

#78000
0!
0$

#79000
1!
1$
b111 '

#80000
0!
0$

#81000
1!
1$
b1000 '

#82000
0!
0$

#83000
1!
1$
b1001 '

#84000
0!
0$

#85000
1!
0#
1$
0&
b0 '

#86000
0!
0$

#87000
1!
1$
b1 '

#88000
0!
0$

#89000
1!
1$
b10 '

#90000
0!
0$

#91000
1!
1$
b11 '

#92000
0!
0$

#93000
1!
1$
b100 '

#94000
0!
0$

#95000
1!
1$
b101 '

#96000
0!
0$

#97000
1!
1$
b110 '

#98000
0!
0$

#99000
1!
1$
b111 '

#100000
0!
0$

#101000
1!
1$
b1000 '

#102000
0!
0$

#103000
1!
1$
b1001 '

#104000
0!
0$

#105000
1!
1#
1$
1&
b0 '

#106000
0!
0$

#107000
1!
1$
b1 '

#108000
0!
0$

#109000
1!
1$
b10 '

#110000
0!
0$

#111000
1!
1$
b11 '

#112000
0!
0$

#113000
1!
1$
b100 '

#114000
0!
0$

#115000
1!
1$
b101 '

#116000
0!
0$

#117000
1!
1$
b110 '

#118000
0!
0$

#119000
1!
1$
b111 '

#120000
0!
0$

#121000
1!
1$
b1000 '

#122000
0!
0$

#123000
1!
1$
b1001 '

#124000
0!
0$

#125000
1!
0#
1$
0&
b0 '

#126000
0!
0$

#127000
1!
1$
b1 '

#128000
0!
0$

#129000
1!
1$
b10 '

#130000
0!
0$

#131000
1!
1$
b11 '

#132000
0!
0$

#133000
1!
1$
b100 '
