T02/T02_Stopwatch_Project/T02_Stopwatch_Project.srcs/sources_1/new/s_to_mmss.v
`timescale 1ns / 1ps
//////////////////////////////////////////////////////////////////////////////////
// Company: 
// Engineer: 
// 
// Create Date: 31.03.2025 16:48:54
// Design Name: 
// Module Name: s_to_mmss
// Project Name: 
// Target Devices: 
// Tool Versions: 
// Description: 
// 
// Dependencies: 
// 
// Revision:
// Revision 0.01 - File Created
// Additional Comments:
// 
//////////////////////////////////////////////////////////////////////////////////

module s_to_mmss(
    input [31:0] s,
    input clk,          // This device relies on the master 100MHz clock to perform simple division
    output reg [31:0] mm,
    output reg [31:0] ss
    );
    
    // We use simple primary school style division, keep subtracting until we cannot subtract anymore and we get our quotient and remainder :)
    reg [2:0]state;
    reg signed [31:0]quotient;
    reg signed [31:0]remainder;
    reg signed [31:0]temp;
    
    initial quotient = 0;
    initial remainder = 0;
    initial state = 0;
    initial temp = 0;
    initial mm = 0;
    initial ss = 0;
    
    
    always @(posedge clk) begin
        // Load from inputs
        if (state == 0) begin
            // Load seconds into the temp register
            temp <= s;
            
            // Reset quotient and remainders
            quotient <= 0;
            remainder <= 0;
            
            // Preserve output register values
            mm <= mm;
            ss <= ss;
            
            // Transition to state 0 (calculating state 1)
            state <= 1;
        end
        
        else if (state == 1) begin
            // Save temp to register, before trying to calculate quotient
            remainder <= temp;
            
            state <= 2;
        end
        
        else if (state == 2) begin
            temp <= temp - 60; // Perform division by subtracting 60 repeatedly
            
            state <= 3;
        end
        
        else if (state == 3) begin
            if (temp < 0) begin
                // Ignore the result, we've reached minimum, preserve quotient and save results to output regs
                quotient <= quotient;
                remainder <= remainder;
                state <= 4;
            end else begin
                // Continue subtracting
                quotient <= quotient + 1;
                remainder <= remainder;
                state <= 1;
            end
        end
        
        // Save data, and go back to the beginning
        else begin
            mm <= quotient;
            ss <= remainder;
        
            state <= 0;
        end
    
    end
    
endmodule

T02/T02_Stopwatch_Project/T02_Stopwatch_Project.srcs/mmss_sims/new/tb.v
`timescale 1ns / 1ps
//////////////////////////////////////////////////////////////////////////////////
// Company: 
// Engineer: 
// 
// Create Date: 01.04.2025 09:36:40
// Design Name: 
// Module Name: tb
// Project Name: 
// Target Devices: 
// Tool Versions: 
// Description: 
// 
// Dependencies: 
// 
// Revision:
// Revision 0.01 - File Created
// Additional Comments:
// 
//////////////////////////////////////////////////////////////////////////////////


module tb;
    // Inputs
    reg [31:0]s;
    reg clk;
    
    // Outputs
    wire [31:0]mm;
    wire [31:0]ss;

    s_to_mmss dut(s, clk, mm, ss);
    
    // Clock generation
always begin
    #1 clk = ~clk;
end

initial begin
    $dumpfile("tb.vcd");
    $dumpvars(0,tb);
    $dumpon;
    
    // Initialise signals at start of simulation
    s = 0;
    clk = 0;
    
    // Simulation
//    #100 s = 30;
//    #100 s = 56;
//    #100 s = 60;
//    #100 s = 62;
//    #100 s = 67;
    #100 s = 9999;
    #2000 s = 3600;
    #2000 $finish;

    $dumpoff;
end

endmodule

T02/T02_Stopwatch_Project/T02_Stopwatch_Project.sim/mmss_sims/behav/xsim/tb.vcd
$date
   Tue Apr  1 16:56:08 2025
$end

$version
  2023.2
  $dumpfile ("tb.vcd") 
$end

$timescale
  1ps
$end

$scope module tb $end
$var reg 32 ! s [31:0] $end
$var reg 1 " clk $end
$var wire 32 # mm [31:0] $end
$var wire 32 $ ss [31:0] $end
$scope module dut $end
$var wire 32 % s [31:0] $end
$var wire 1 & clk $end
$var reg 32 ' mm [31:0] $end
$var reg 32 ( ss [31:0] $end
$var reg 3 ) state [2:0] $end
$var reg 32 * quotient [31:0] $end
$var reg 32 + remainder [31:0] $end
$var reg 32 , temp [31:0] $end
$upscope $end
$upscope $end
$enddefinitions $end

#0
$dumpvars
b0 !
0"
b0 #
b0 $
b0 %
0&
b0 '
b0 (
b0 )
b0 *
b0 +
b0 ,
$end

#1000
1"
1&
b1 )

#2000
0"
0&

#3000
1"
1&
b10 )

#4000
0"
0&

#5000
1"
1&
b11 )
b11111111111111111111111111000100 ,

#6000
0"
0&

#7000
1"
1&
b100 )

#8000
0"
0&

#9000
1"
1&
b0 )

#10000
0"
0&

#11000
1"
1&
b1 )
b0 ,

#12000
0"
0&

#13000
1"
1&
b10 )

#14000
0"
0&

#15000
1"
1&
b11 )
b11111111111111111111111111000100 ,

#16000
0"
0&

#17000
1"
1&
b100 )

#18000
0"
0&

#19000
1"
1&
b0 )

#20000
0"
0&

#21000
1"
1&
b1 )
b0 ,

#22000
0"
0&

#23000
1"
1&
b10 )

#24000
0"
0&

#25000
1"
1&
b11 )
b11111111111111111111111111000100 ,

#26000
0"
0&

#27000
1"
1&
b100 )

#28000
0"
0&

#29000
1"
1&
b0 )

#30000
0"
0&

#31000
1"
1&
b1 )
b0 ,

#32000
0"
0&

#33000
1"
1&
b10 )

#34000
0"
0&

#35000
1"
1&
b11 )
b11111111111111111111111111000100 ,

#36000
0"
0&

#37000
1"
1&
b100 )

#38000
0"
0&

#39000
1"
1&
b0 )

#40000
0"
0&

#41000
1"
1&
b1 )
b0 ,

#42000
0"
0&

#43000
1"
1&
b10 )

#44000
0"
0&

#45000
1"
1&
b11 )
b11111111111111111111111111000100 ,

#46000
0"
0&

#47000
1"
1&
b100 )

#48000
0"
0&

#49000
1"
1&
b0 )

#50000
0"
0&

#51000
1"
1&
b1 )
b0 ,

#52000
0"
0&

#53000
1"
1&
b10 )

#54000
0"
0&

#55000
1"
1&
b11 )
b11111111111111111111111111000100 ,

#56000
0"
0&

#57000
1"
1&
b100 )

#58000
0"
0&

#59000
1"
1&
b0 )

#60000
0"
0&

#61000
1"
1&
b1 )
b0 ,

#62000
0"
0&

#63000
1"
1&
b10 )

#64000
0"
0&

#65000
1"
1&
b11 )
b11111111111111111111111111000100 ,

#66000
0"
0&

#67000
1"
1&
b100 )

#68000
0"
0&

#69000
1"
1&
b0 )

#70000
0"
0&

#71000
1"
1&
b1 )
b0 ,

#72000
0"
0&

#73000
1"
1&
b10 )

#74000
0"
0&

#75000
1"
1&
b11 )
b11111111111111111111111111000100 ,

#76000
0"
0&

#77000
1"
1&
b100 )

#78000
0"
0&

#79000
1"
1&
b0 )

#80000
0"
0&

#81000
1"
1&
b1 )
b0 ,

#82000
0"
0&

#83000
1"
1&
b10 )

#84000
0"
0&

#85000
1"
1&
b11 )
b11111111111111111111111111000100 ,

#86000
0"
0&

#87000
1"
1&
b100 )

#88000
0"
0&

#89000
1"
1&
b0 )

#90000
0"
0&

#91000
1"
1&
b1 )
b0 ,

#92000
0"
0&

#93000
1"
1&
b10 )

#94000
0"
0&

#95000
1"
1&
b11 )
b11111111111111111111111111000100 ,

#96000
0"
0&

#97000
1"
1&
b100 )

#98000
0"
0&

#99000
1"
1&
b0 )

#100000
b10011100001111 !
0"
b10011100001111 %
0&

#101000
1"
1&
b1 )
b10011100001111 ,

#102000
0"
0&

#103000
1"
1&
b10 )
b10011100001111 +

#104000
0"
0&

#105000
1"
1&
b11 )
b10011011010011 ,

#106000
0"
0&

#107000
1"
1&
b1 )
b1 *

#108000
0"
0&

#109000
1"
1&
b10 )
b10011011010011 +

#110000
0"
0&

#111000
1"
1&
b11 )
b10011010010111 ,

#112000
0"
0&

#113000
1"
1&
b1 )
b10 *

#114000
0"
0&

#115000
1"
1&
b10 )
b10011010010111 +

#116000
0"
0&

#117000
1"
1&
b11 )
b10011001011011 ,

#118000
0"
0&

#119000
1"
1&
b1 )
b11 *

#120000
0"
0&

#121000
1"
1&
b10 )
b10011001011011 +

#122000
0"
0&

#123000
1"
1&
b11 )
b10011000011111 ,

#124000
0"
0&

#125000
1"
1&
b1 )
b100 *

#126000
0"
0&

#127000
1"
1&
b10 )
b10011000011111 +

#128000
0"
0&

#129000
1"
1&
b11 )
b10010111100011 ,

#130000
0"
0&

#131000
1"
1&
b1 )
b101 *

#132000
0"
0&

#133000
1"
1&
b10 )
b10010111100011 +

#134000
0"
0&

#135000
1"
1&
b11 )
b10010110100111 ,

#136000
0"
0&

#137000
1"
1&
b1 )
b110 *

#138000
0"
0&

#139000
1"
1&
b10 )
b10010110100111 +

#140000
0"
0&

#141000
1"
1&
b11 )
b10010101101011 ,

#142000
0"
0&

#143000
1"
1&
b1 )
b111 *

#144000
0"
0&

#145000
1"
1&
b10 )
b10010101101011 +

#146000
0"
0&

#147000
1"
1&
b11 )
b10010100101111 ,

#148000
0"
0&

#149000
1"
1&
b1 )
b1000 *

#150000
0"
0&

#151000
1"
1&
b10 )
b10010100101111 +

#152000
0"
0&

#153000
1"
1&
b11 )
b10010011110011 ,

#154000
0"
0&

#155000
1"
1&
b1 )
b1001 *

#156000
0"
0&

#157000
1"
1&
b10 )
b10010011110011 +

#158000
0"
0&

#159000
1"
1&
b11 )
b10010010110111 ,

#160000
0"
0&

#161000
1"
1&
b1 )
b1010 *

#162000
0"
0&

#163000
1"
1&
b10 )
b10010010110111 +

#164000
0"
0&

#165000
1"
1&
b11 )
b10010001111011 ,

#166000
0"
0&

#167000
1"
1&
b1 )
b1011 *

#168000
0"
0&

#169000
1"
1&
b10 )
b10010001111011 +

#170000
0"
0&

#171000
1"
1&
b11 )
b10010000111111 ,

#172000
0"
0&

#173000
1"
1&
b1 )
b1100 *

#174000
0"
0&

#175000
1"
1&
b10 )
b10010000111111 +

#176000
0"
0&

#177000
1"
1&
b11 )
b10010000000011 ,

#178000
0"
0&

#179000
1"
1&
b1 )
b1101 *

#180000
0"
0&

#181000
1"
1&
b10 )
b10010000000011 +

#182000
0"
0&

#183000
1"
1&
b11 )
b10001111000111 ,

#184000
0"
0&

#185000
1"
1&
b1 )
b1110 *

#186000
0"
0&

#187000
1"
1&
b10 )
b10001111000111 +

#188000
0"
0&

#189000
1"
1&
b11 )
b10001110001011 ,

#190000
0"
0&

#191000
1"
1&
b1 )
b1111 *

#192000
0"
0&

#193000
1"
1&
b10 )
b10001110001011 +

#194000
0"
0&

#195000
1"
1&
b11 )
b10001101001111 ,

#196000
0"
0&

#197000
1"
1&
b1 )
b10000 *

#198000
0"
0&

#199000
1"
1&
b10 )
b10001101001111 +

#200000
0"
0&

#201000
1"
1&
b11 )
b10001100010011 ,

#202000
0"
0&

#203000
1"
1&
b1 )
b10001 *

#204000
0"
0&

#205000
1"
1&
b10 )
b10001100010011 +

#206000
0"
0&

#207000
1"
1&
b11 )
b10001011010111 ,

#208000
0"
0&

#209000
1"
1&
b1 )
b10010 *

#210000
0"
0&

#211000
1"
1&
b10 )
b10001011010111 +

#212000
0"
0&

#213000
1"
1&
b11 )
b10001010011011 ,

#214000
0"
0&

#215000
1"
1&
b1 )
b10011 *

#216000
0"
0&

#217000
1"
1&
b10 )
b10001010011011 +

#218000
0"
0&

#219000
1"
1&
b11 )
b10001001011111 ,

#220000
0"
0&

#221000
1"
1&
b1 )
b10100 *

#222000
0"
0&

#223000
1"
1&
b10 )
b10001001011111 +

#224000
0"
0&

#225000
1"
1&
b11 )
b10001000100011 ,

#226000
0"
0&

#227000
1"
1&
b1 )
b10101 *

#228000
0"
0&

#229000
1"
1&
b10 )
b10001000100011 +

#230000
0"
0&

#231000
1"
1&
b11 )
b10000111100111 ,

#232000
0"
0&

#233000
1"
1&
b1 )
b10110 *

#234000
0"
0&

#235000
1"
1&
b10 )
b10000111100111 +

#236000
0"
0&

#237000
1"
1&
b11 )
b10000110101011 ,

#238000
0"
0&

#239000
1"
1&
b1 )
b10111 *

#240000
0"
0&

#241000
1"
1&
b10 )
b10000110101011 +

#242000
0"
0&

#243000
1"
1&
b11 )
b10000101101111 ,

#244000
0"
0&

#245000
1"
1&
b1 )
b11000 *

#246000
0"
0&

#247000
1"
1&
b10 )
b10000101101111 +

#248000
0"
0&

#249000
1"
1&
b11 )
b10000100110011 ,

#250000
0"
0&

#251000
1"
1&
b1 )
b11001 *

#252000
0"
0&

#253000
1"
1&
b10 )
b10000100110011 +

#254000
0"
0&

#255000
1"
1&
b11 )
b10000011110111 ,

#256000
0"
0&

#257000
1"
1&
b1 )
b11010 *

#258000
0"
0&

#259000
1"
1&
b10 )
b10000011110111 +

#260000
0"
0&

#261000
1"
1&
b11 )
b10000010111011 ,

#262000
0"
0&

#263000
1"
1&
b1 )
b11011 *

#264000
0"
0&

#265000
1"
1&
b10 )
b10000010111011 +

#266000
0"
0&

#267000
1"
1&
b11 )
b10000001111111 ,

#268000
0"
0&

#269000
1"
1&
b1 )
b11100 *

#270000
0"
0&

#271000
1"
1&
b10 )
b10000001111111 +

#272000
0"
0&

#273000
1"
1&
b11 )
b10000001000011 ,

#274000
0"
0&

#275000
1"
1&
b1 )
b11101 *

#276000
0"
0&

#277000
1"
1&
b10 )
b10000001000011 +

#278000
0"
0&

#279000
1"
1&
b11 )
b10000000000111 ,

#280000
0"
0&

#281000
1"
1&
b1 )
b11110 *

#282000
0"
0&

#283000
1"
1&
b10 )
b10000000000111 +

#284000
0"
0&

#285000
1"
1&
b11 )
b1111111001011 ,

#286000
0"
0&

#287000
1"
1&
b1 )
b11111 *

#288000
0"
0&

#289000
1"
1&
b10 )
b1111111001011 +

#290000
0"
0&

#291000
1"
1&
b11 )
b1111110001111 ,

#292000
0"
0&

#293000
1"
1&
b1 )
b100000 *

#294000
0"
0&

#295000
1"
1&
b10 )
b1111110001111 +

#296000
0"
0&

#297000
1"
1&
b11 )
b1111101010011 ,

#298000
0"
0&

#299000
1"
1&
b1 )
b100001 *

#300000
0"
0&

#301000
1"
1&
b10 )
b1111101010011 +

#302000
0"
0&

#303000
1"
1&
b11 )
b1111100010111 ,

#304000
0"
0&

#305000
1"
1&
b1 )
b100010 *

#306000
0"
0&

#307000
1"
1&
b10 )
b1111100010111 +

#308000
0"
0&

#309000
1"
1&
b11 )
b1111011011011 ,

#310000
0"
0&

#311000
1"
1&
b1 )
b100011 *

#312000
0"
0&

#313000
1"
1&
b10 )
b1111011011011 +

#314000
0"
0&

#315000
1"
1&
b11 )
b1111010011111 ,

#316000
0"
0&

#317000
1"
1&
b1 )
b100100 *

#318000
0"
0&

#319000
1"
1&
b10 )
b1111010011111 +

#320000
0"
0&

#321000
1"
1&
b11 )
b1111001100011 ,

#322000
0"
0&

#323000
1"
1&
b1 )
b100101 *

#324000
0"
0&

#325000
1"
1&
b10 )
b1111001100011 +

#326000
0"
0&

#327000
1"
1&
b11 )
b1111000100111 ,

#328000
0"
0&

#329000
1"
1&
b1 )
b100110 *

#330000
0"
0&

#331000
1"
1&
b10 )
b1111000100111 +

#332000
0"
0&

#333000
1"
1&
b11 )
b1110111101011 ,

#334000
0"
0&

#335000
1"
1&
b1 )
b100111 *

#336000
0"
0&

#337000
1"
1&
b10 )
b1110111101011 +

#338000
0"
0&

#339000
1"
1&
b11 )
b1110110101111 ,

#340000
0"
0&

#341000
1"
1&
b1 )
b101000 *

#342000
0"
0&

#343000
1"
1&
b10 )
b1110110101111 +

#344000
0"
0&

#345000
1"
1&
b11 )
b1110101110011 ,

#346000
0"
0&

#347000
1"
1&
b1 )
b101001 *

#348000
0"
0&

#349000
1"
1&
b10 )
b1110101110011 +

#350000
0"
0&

#351000
1"
1&
b11 )
b1110100110111 ,

#352000
0"
0&

#353000
1"
1&
b1 )
b101010 *

#354000
0"
0&

#355000
1"
1&
b10 )
b1110100110111 +

#356000
0"
0&

#357000
1"
1&
b11 )
b1110011111011 ,

#358000
0"
0&

#359000
1"
1&
b1 )
b101011 *

#360000
0"
0&

#361000
1"
1&
b10 )
b1110011111011 +

#362000
0"
0&

#363000
1"
1&
b11 )
b1110010111111 ,

#364000
0"
0&

#365000
1"
1&
b1 )
b101100 *

#366000
0"
0&

#367000
1"
1&
b10 )
b1110010111111 +

#368000
0"
0&

#369000
1"
1&
b11 )
b1110010000011 ,

#370000
0"
0&

#371000
1"
1&
b1 )
b101101 *

#372000
0"
0&

#373000
1"
1&
b10 )
b1110010000011 +

#374000
0"
0&

#375000
1"
1&
b11 )
b1110001000111 ,

#376000
0"
0&

#377000
1"
1&
b1 )
b101110 *

#378000
0"
0&

#379000
1"
1&
b10 )
b1110001000111 +

#380000
0"
0&

#381000
1"
1&
b11 )
b1110000001011 ,

#382000
0"
0&

#383000
1"
1&
b1 )
b101111 *

#384000
0"
0&

#385000
1"
1&
b10 )
b1110000001011 +

#386000
0"
0&

#387000
1"
1&
b11 )
b1101111001111 ,

#388000
0"
0&

#389000
1"
1&
b1 )
b110000 *

#390000
0"
0&

#391000
1"
1&
b10 )
b1101111001111 +

#392000
0"
0&

#393000
1"
1&
b11 )
b1101110010011 ,

#394000
0"
0&

#395000
1"
1&
b1 )
b110001 *

#396000
0"
0&

#397000
1"
1&
b10 )
b1101110010011 +

#398000
0"
0&

#399000
1"
1&
b11 )
b1101101010111 ,

#400000
0"
0&

#401000
1"
1&
b1 )
b110010 *

#402000
0"
0&

#403000
1"
1&
b10 )
b1101101010111 +

#404000
0"
0&

#405000
1"
1&
b11 )
b1101100011011 ,

#406000
0"
0&

#407000
1"
1&
b1 )
b110011 *

#408000
0"
0&

#409000
1"
1&
b10 )
b1101100011011 +

#410000
0"
0&

#411000
1"
1&
b11 )
b1101011011111 ,

#412000
0"
0&

#413000
1"
1&
b1 )
b110100 *

#414000
0"
0&

#415000
1"
1&
b10 )
b1101011011111 +

#416000
0"
0&

#417000
1"
1&
b11 )
b1101010100011 ,

#418000
0"
0&

#419000
1"
1&
b1 )
b110101 *

#420000
0"
0&

#421000
1"
1&
b10 )
b1101010100011 +

#422000
0"
0&

#423000
1"
1&
b11 )
b1101001100111 ,

#424000
0"
0&

#425000
1"
1&
b1 )
b110110 *

#426000
0"
0&

#427000
1"
1&
b10 )
b1101001100111 +

#428000
0"
0&

#429000
1"
1&
b11 )
b1101000101011 ,

#430000
0"
0&

#431000
1"
1&
b1 )
b110111 *

#432000
0"
0&

#433000
1"
1&
b10 )
b1101000101011 +

#434000
0"
0&

#435000
1"
1&
b11 )
b1100111101111 ,

#436000
0"
0&

#437000
1"
1&
b1 )
b111000 *

#438000
0"
0&

#439000
1"
1&
b10 )
b1100111101111 +

#440000
0"
0&

#441000
1"
1&
b11 )
b1100110110011 ,

#442000
0"
0&

#443000
1"
1&
b1 )
b111001 *

#444000
0"
0&

#445000
1"
1&
b10 )
b1100110110011 +

#446000
0"
0&

#447000
1"
1&
b11 )
b1100101110111 ,

#448000
0"
0&

#449000
1"
1&
b1 )
b111010 *

#450000
0"
0&

#451000
1"
1&
b10 )
b1100101110111 +

#452000
0"
0&

#453000
1"
1&
b11 )
b1100100111011 ,

#454000
0"
0&

#455000
1"
1&
b1 )
b111011 *

#456000
0"
0&

#457000
1"
1&
b10 )
b1100100111011 +

#458000
0"
0&

#459000
1"
1&
b11 )
b1100011111111 ,

#460000
0"
0&

#461000
1"
1&
b1 )
b111100 *

#462000
0"
0&

#463000
1"
1&
b10 )
b1100011111111 +

#464000
0"
0&

#465000
1"
1&
b11 )
b1100011000011 ,

#466000
0"
0&

#467000
1"
1&
b1 )
b111101 *

#468000
0"
0&

#469000
1"
1&
b10 )
b1100011000011 +

#470000
0"
0&

#471000
1"
1&
b11 )
b1100010000111 ,

#472000
0"
0&

#473000
1"
1&
b1 )
b111110 *

#474000
0"
0&

#475000
1"
1&
b10 )
b1100010000111 +

#476000
0"
0&

#477000
1"
1&
b11 )
b1100001001011 ,

#478000
0"
0&

#479000
1"
1&
b1 )
b111111 *

#480000
0"
0&

#481000
1"
1&
b10 )
b1100001001011 +

#482000
0"
0&

#483000
1"
1&
b11 )
b1100000001111 ,

#484000
0"
0&

#485000
1"
1&
b1 )
b1000000 *

#486000
0"
0&

#487000
1"
1&
b10 )
b1100000001111 +

#488000
0"
0&

#489000
1"
1&
b11 )
b1011111010011 ,

#490000
0"
0&

#491000
1"
1&
b1 )
b1000001 *

#492000
0"
0&

#493000
1"
1&
b10 )
b1011111010011 +

#494000
0"
0&

#495000
1"
1&
b11 )
b1011110010111 ,

#496000
0"
0&

#497000
1"
1&
b1 )
b1000010 *

#498000
0"
0&

#499000
1"
1&
b10 )
b1011110010111 +

#500000
0"
0&

#501000
1"
1&
b11 )
b1011101011011 ,

#502000
0"
0&

#503000
1"
1&
b1 )
b1000011 *

#504000
0"
0&

#505000
1"
1&
b10 )
b1011101011011 +

#506000
0"
0&

#507000
1"
1&
b11 )
b1011100011111 ,

#508000
0"
0&

#509000
1"
1&
b1 )
b1000100 *

#510000
0"
0&

#511000
1"
1&
b10 )
b1011100011111 +

#512000
0"
0&

#513000
1"
1&
b11 )
b1011011100011 ,

#514000
0"
0&

#515000
1"
1&
b1 )
b1000101 *

#516000
0"
0&

#517000
1"
1&
b10 )
b1011011100011 +

#518000
0"
0&

#519000
1"
1&
b11 )
b1011010100111 ,

#520000
0"
0&

#521000
1"
1&
b1 )
b1000110 *

#522000
0"
0&

#523000
1"
1&
b10 )
b1011010100111 +

#524000
0"
0&

#525000
1"
1&
b11 )
b1011001101011 ,

#526000
0"
0&

#527000
1"
1&
b1 )
b1000111 *

#528000
0"
0&

#529000
1"
1&
b10 )
b1011001101011 +

#530000
0"
0&

#531000
1"
1&
b11 )
b1011000101111 ,

#532000
0"
0&

#533000
1"
1&
b1 )
b1001000 *

#534000
0"
0&

#535000
1"
1&
b10 )
b1011000101111 +

#536000
0"
0&

#537000
1"
1&
b11 )
b1010111110011 ,

#538000
0"
0&

#539000
1"
1&
b1 )
b1001001 *

#540000
0"
0&

#541000
1"
1&
b10 )
b1010111110011 +

#542000
0"
0&

#543000
1"
1&
b11 )
b1010110110111 ,

#544000
0"
0&

#545000
1"
1&
b1 )
b1001010 *

#546000
0"
0&

#547000
1"
1&
b10 )
b1010110110111 +

#548000
0"
0&

#549000
1"
1&
b11 )
b1010101111011 ,

#550000
0"
0&

#551000
1"
1&
b1 )
b1001011 *

#552000
0"
0&

#553000
1"
1&
b10 )
b1010101111011 +

#554000
0"
0&

#555000
1"
1&
b11 )
b1010100111111 ,

#556000
0"
0&

#557000
1"
1&
b1 )
b1001100 *

#558000
0"
0&

#559000
1"
1&
b10 )
b1010100111111 +

#560000
0"
0&

#561000
1"
1&
b11 )
b1010100000011 ,

#562000
0"
0&

#563000
1"
1&
b1 )
b1001101 *

#564000
0"
0&

#565000
1"
1&
b10 )
b1010100000011 +

#566000
0"
0&

#567000
1"
1&
b11 )
b1010011000111 ,

#568000
0"
0&

#569000
1"
1&
b1 )
b1001110 *

#570000
0"
0&

#571000
1"
1&
b10 )
b1010011000111 +

#572000
0"
0&

#573000
1"
1&
b11 )
b1010010001011 ,

#574000
0"
0&

#575000
1"
1&
b1 )
b1001111 *

#576000
0"
0&

#577000
1"
1&
b10 )
b1010010001011 +

#578000
0"
0&

#579000
1"
1&
b11 )
b1010001001111 ,

#580000
0"
0&

#581000
1"
1&
b1 )
b1010000 *

#582000
0"
0&

#583000
1"
1&
b10 )
b1010001001111 +

#584000
0"
0&

#585000
1"
1&
b11 )
b1010000010011 ,

#586000
0"
0&

#587000
1"
1&
b1 )
b1010001 *

#588000
0"
0&

#589000
1"
1&
b10 )
b1010000010011 +

#590000
0"
0&

#591000
1"
1&
b11 )
b1001111010111 ,

#592000
0"
0&

#593000
1"
1&
b1 )
b1010010 *

#594000
0"
0&

#595000
1"
1&
b10 )
b1001111010111 +

#596000
0"
0&

#597000
1"
1&
b11 )
b1001110011011 ,

#598000
0"
0&

#599000
1"
1&
b1 )
b1010011 *

#600000
0"
0&

#601000
1"
1&
b10 )
b1001110011011 +

#602000
0"
0&

#603000
1"
1&
b11 )
b1001101011111 ,

#604000
0"
0&

#605000
1"
1&
b1 )
b1010100 *

#606000
0"
0&

#607000
1"
1&
b10 )
b1001101011111 +

#608000
0"
0&

#609000
1"
1&
b11 )
b1001100100011 ,

#610000
0"
0&

#611000
1"
1&
b1 )
b1010101 *

#612000
0"
0&

#613000
1"
1&
b10 )
b1001100100011 +

#614000
0"
0&

#615000
1"
1&
b11 )
b1001011100111 ,

#616000
0"
0&

#617000
1"
1&
b1 )
b1010110 *

#618000
0"
0&

#619000
1"
1&
b10 )
b1001011100111 +

#620000
0"
0&

#621000
1"
1&
b11 )
b1001010101011 ,

#622000
0"
0&

#623000
1"
1&
b1 )
b1010111 *

#624000
0"
0&

#625000
1"
1&
b10 )
b1001010101011 +

#626000
0"
0&

#627000
1"
1&
b11 )
b1001001101111 ,

#628000
0"
0&

#629000
1"
1&
b1 )
b1011000 *

#630000
0"
0&

#631000
1"
1&
b10 )
b1001001101111 +

#632000
0"
0&

#633000
1"
1&
b11 )
b1001000110011 ,

#634000
0"
0&

#635000
1"
1&
b1 )
b1011001 *

#636000
0"
0&

#637000
1"
1&
b10 )
b1001000110011 +

#638000
0"
0&

#639000
1"
1&
b11 )
b1000111110111 ,

#640000
0"
0&

#641000
1"
1&
b1 )
b1011010 *

#642000
0"
0&

#643000
1"
1&
b10 )
b1000111110111 +

#644000
0"
0&

#645000
1"
1&
b11 )
b1000110111011 ,

#646000
0"
0&

#647000
1"
1&
b1 )
b1011011 *

#648000
0"
0&

#649000
1"
1&
b10 )
b1000110111011 +

#650000
0"
0&

#651000
1"
1&
b11 )
b1000101111111 ,

#652000
0"
0&

#653000
1"
1&
b1 )
b1011100 *

#654000
0"
0&

#655000
1"
1&
b10 )
b1000101111111 +

#656000
0"
0&

#657000
1"
1&
b11 )
b1000101000011 ,

#658000
0"
0&

#659000
1"
1&
b1 )
b1011101 *

#660000
0"
0&

#661000
1"
1&
b10 )
b1000101000011 +

#662000
0"
0&

#663000
1"
1&
b11 )
b1000100000111 ,

#664000
0"
0&

#665000
1"
1&
b1 )
b1011110 *

#666000
0"
0&

#667000
1"
1&
b10 )
b1000100000111 +

#668000
0"
0&

#669000
1"
1&
b11 )
b1000011001011 ,

#670000
0"
0&

#671000
1"
1&
b1 )
b1011111 *

#672000
0"
0&

#673000
1"
1&
b10 )
b1000011001011 +

#674000
0"
0&

#675000
1"
1&
b11 )
b1000010001111 ,

#676000
0"
0&

#677000
1"
1&
b1 )
b1100000 *

#678000
0"
0&

#679000
1"
1&
b10 )
b1000010001111 +

#680000
0"
0&

#681000
1"
1&
b11 )
b1000001010011 ,

#682000
0"
0&

#683000
1"
1&
b1 )
b1100001 *

#684000
0"
0&

#685000
1"
1&
b10 )
b1000001010011 +

#686000
0"
0&

#687000
1"
1&
b11 )
b1000000010111 ,

#688000
0"
0&

#689000
1"
1&
b1 )
b1100010 *

#690000
0"
0&

#691000
1"
1&
b10 )
b1000000010111 +

#692000
0"
0&

#693000
1"
1&
b11 )
b111111011011 ,

#694000
0"
0&

#695000
1"
1&
b1 )
b1100011 *

#696000
0"
0&

#697000
1"
1&
b10 )
b111111011011 +

#698000
0"
0&

#699000
1"
1&
b11 )
b111110011111 ,

#700000
0"
0&

#701000
1"
1&
b1 )
b1100100 *

#702000
0"
0&

#703000
1"
1&
b10 )
b111110011111 +

#704000
0"
0&

#705000
1"
1&
b11 )
b111101100011 ,

#706000
0"
0&

#707000
1"
1&
b1 )
b1100101 *

#708000
0"
0&

#709000
1"
1&
b10 )
b111101100011 +

#710000
0"
0&

#711000
1"
1&
b11 )
b111100100111 ,

#712000
0"
0&

#713000
1"
1&
b1 )
b1100110 *

#714000
0"
0&

#715000
1"
1&
b10 )
b111100100111 +

#716000
0"
0&

#717000
1"
1&
b11 )
b111011101011 ,

#718000
0"
0&

#719000
1"
1&
b1 )
b1100111 *

#720000
0"
0&

#721000
1"
1&
b10 )
b111011101011 +

#722000
0"
0&

#723000
1"
1&
b11 )
b111010101111 ,

#724000
0"
0&

#725000
1"
1&
b1 )
b1101000 *

#726000
0"
0&

#727000
1"
1&
b10 )
b111010101111 +

#728000
0"
0&

#729000
1"
1&
b11 )
b111001110011 ,

#730000
0"
0&

#731000
1"
1&
b1 )
b1101001 *

#732000
0"
0&

#733000
1"
1&
b10 )
b111001110011 +

#734000
0"
0&

#735000
1"
1&
b11 )
b111000110111 ,

#736000
0"
0&

#737000
1"
1&
b1 )
b1101010 *

#738000
0"
0&

#739000
1"
1&
b10 )
b111000110111 +

#740000
0"
0&

#741000
1"
1&
b11 )
b110111111011 ,

#742000
0"
0&

#743000
1"
1&
b1 )
b1101011 *

#744000
0"
0&

#745000
1"
1&
b10 )
b110111111011 +

#746000
0"
0&

#747000
1"
1&
b11 )
b110110111111 ,

#748000
0"
0&

#749000
1"
1&
b1 )
b1101100 *

#750000
0"
0&

#751000
1"
1&
b10 )
b110110111111 +

#752000
0"
0&

#753000
1"
1&
b11 )
b110110000011 ,

#754000
0"
0&

#755000
1"
1&
b1 )
b1101101 *

#756000
0"
0&

#757000
1"
1&
b10 )
b110110000011 +

#758000
0"
0&

#759000
1"
1&
b11 )
b110101000111 ,

#760000
0"
0&

#761000
1"
1&
b1 )
b1101110 *

#762000
0"
0&

#763000
1"
1&
b10 )
b110101000111 +

#764000
0"
0&

#765000
1"
1&
b11 )
b110100001011 ,

#766000
0"
0&

#767000
1"
1&
b1 )
b1101111 *

#768000
0"
0&

#769000
1"
1&
b10 )
b110100001011 +

#770000
0"
0&

#771000
1"
1&
b11 )
b110011001111 ,

#772000
0"
0&

#773000
1"
1&
b1 )
b1110000 *

#774000
0"
0&

#775000
1"
1&
b10 )
b110011001111 +

#776000
0"
0&

#777000
1"
1&
b11 )
b110010010011 ,

#778000
0"
0&

#779000
1"
1&
b1 )
b1110001 *

#780000
0"
0&

#781000
1"
1&
b10 )
b110010010011 +

#782000
0"
0&

#783000
1"
1&
b11 )
b110001010111 ,

#784000
0"
0&

#785000
1"
1&
b1 )
b1110010 *

#786000
0"
0&

#787000
1"
1&
b10 )
b110001010111 +

#788000
0"
0&

#789000
1"
1&
b11 )
b110000011011 ,

#790000
0"
0&

#791000
1"
1&
b1 )
b1110011 *

#792000
0"
0&

